boaviztapi/__init__.py
boaviztapi/data/archetypes/cloud/aws.csv
boaviztapi/data/archetypes/cloud/azure.csv
boaviztapi/data/archetypes/cloud/cloud.fmt
boaviztapi/data/archetypes/cloud/gcp.csv
boaviztapi/data/archetypes/cloud/providers.csv
boaviztapi/data/archetypes/cloud/scaleway.csv
boaviztapi/data/archetypes/components/case.csv
boaviztapi/data/archetypes/components/cpu.csv
boaviztapi/data/archetypes/components/gpu.csv
boaviztapi/data/archetypes/components/hdd.csv
boaviztapi/data/archetypes/components/power_supply.csv
boaviztapi/data/archetypes/components/ram.csv
boaviztapi/data/archetypes/components/ssd.csv
boaviztapi/data/archetypes/iot_device.csv
boaviztapi/data/archetypes/server.csv
boaviztapi/data/archetypes/server.fmt
boaviztapi/data/archetypes/user_terminal.csv
boaviztapi/data/consumption_profile/cpu/cpu_profile.csv
boaviztapi/data/crowdsourcing/ademe_base_impacts_negaoctet.csv
boaviztapi/data/crowdsourcing/cpu_specs.csv
boaviztapi/data/crowdsourcing/cpu_specs.fmt
boaviztapi/data/crowdsourcing/electrical_mix.csv
boaviztapi/data/crowdsourcing/iot_factors_tide.csv
boaviztapi/data/crowdsourcing/missing_cpu_manufacture.csv
boaviztapi/data/crowdsourcing/ram_manufacture.csv
boaviztapi/data/crowdsourcing/ssd_manufacture.csv
boaviztapi/data/factors.yml
boaviztapi/data/utils/complete_AWS_EC2/README.md
boaviztapi/data/utils/complete_AWS_EC2/addData.go
boaviztapi/data/utils/complete_AWS_EC2/addData.md
boaviztapi/data/utils/complete_AWS_EC2/go.mod
boaviztapi/data/utils/complete_AWS_EC2/vantage-export.csv
boaviztapi/data/utils/complete_Azure_VMs/.gitignore
boaviztapi/data/utils/complete_Azure_VMs/README.md
boaviztapi/data/utils/complete_Azure_VMs/RESULTS.md
boaviztapi/data/utils/complete_Azure_VMs/aws_result.csv
boaviztapi/data/utils/complete_Azure_VMs/azure_instances.csv
boaviztapi/data/utils/complete_Azure_VMs/azure_servers.csv
boaviztapi/data/utils/complete_Azure_VMs/azure_update_workflow.webp
boaviztapi/data/utils/complete_Azure_VMs/azure_vms_from_vantage.csv
boaviztapi-2.0.1.dist-info/METADATA
boaviztapi-2.0.1.dist-info/WHEEL
boaviztapi-2.0.1.dist-info/licenses/LICENSE
boaviztapi-2.0.1.dist-info/RECORD
