Metadata-Version: 2.4
Name: boaviztapi
Version: 2.0.1
Summary: An API to access Boavizta's methodologies and footprint reference data
License-File: LICENSE
Requires-Python: >=3.11,<4.0
Classifier: Programming Language :: Python :: 3
Classifier: Programming Language :: Python :: 3.11
Classifier: Programming Language :: Python :: 3.12
Classifier: Programming Language :: Python :: 3.13
Classifier: Programming Language :: Python :: 3.14
Requires-Dist: aiofile (>=3.9.0,<4.0.0)
Requires-Dist: aiohttp (>=3.13.3,<4.0.0)
Requires-Dist: fastapi (>=0.128.0,<0.129.0)
Requires-Dist: importlib-metadata (>=8.7.1,<9.0.0)
Requires-Dist: mangum (>=0.20.0,<0.21.0)
Requires-Dist: markdown (>=3.10,<4.0)
Requires-Dist: numpy (>=2.4.1,<3.0.0)
Requires-Dist: pandas (>=2.3.3,<3.0.0)
Requires-Dist: pydantic (>=2.12.5,<3.0.0)
Requires-Dist: pydantic-settings (>=2.0,<3.0)
Requires-Dist: pyyaml (>=6.0.3,<7.0.0)
Requires-Dist: rapidfuzz (>=3.14.3,<4.0.0)
Requires-Dist: scipy (>=1.17.0,<2.0.0)
Requires-Dist: toml (>=0.10.2,<0.11.0)
Requires-Dist: urllib3 (>=2.6.3,<3.0.0)
Requires-Dist: uvicorn (>=0.40,<0.41)
